{
	"name": "pipeline5",
	"properties": {
		"activities": [
			{
				"name": "ForEach1",
				"type": "ForEach",
				"dependsOn": [],
				"userProperties": [],
				"typeProperties": {
					"items": {
						"value": "@pipeline().parameters.outputfolders",
						"type": "Expression"
					},
					"isSequential": true,
					"activities": [
						{
							"name": "Copy data1",
							"type": "Copy",
							"dependsOn": [],
							"policy": {
								"timeout": "7.00:00:00",
								"retry": 0,
								"retryIntervalInSeconds": 30,
								"secureOutput": false,
								"secureInput": false
							},
							"userProperties": [],
							"typeProperties": {
								"source": {
									"type": "BinarySource",
									"storeSettings": {
										"type": "AzureBlobStorageReadSettings",
										"recursive": true
									},
									"formatSettings": {
										"type": "BinaryReadSettings"
									}
								},
								"sink": {
									"type": "BinarySink",
									"storeSettings": {
										"type": "AzureBlobStorageWriteSettings"
									}
								},
								"enableStaging": false
							},
							"inputs": [
								{
									"referenceName": "input",
									"type": "DatasetReference"
								}
							],
							"outputs": [
								{
									"referenceName": "demokavyaoutput",
									"type": "DatasetReference",
									"parameters": {
										"foldername": {
											"value": "@item()",
											"type": "Expression"
										}
									}
								}
							]
						}
					]
				}
			}
		],
		"parameters": {
			"outputfolders": {
				"type": "array",
				"defaultValue": [
					1,
					2,
					3
				]
			}
		},
		"annotations": [],
		"lastPublishTime": "2022-06-30T09:17:17Z"
	},
	"type": "Microsoft.DataFactory/factories/pipelines"
}